kognic/studio/proto/messages_pb2.py
kognic/studio/proto/messages_pb2.pyi
kognic_studio_proto-0.0.0.dist-info/METADATA
kognic_studio_proto-0.0.0.dist-info/WHEEL
kognic_studio_proto-0.0.0.dist-info/top_level.txt
kognic_studio_proto-0.0.0.dist-info/RECORD
